kitir/__init__.py
kitir/environment.py
kitir/utils.py
kitir/_libs/__init__.py
kitir/_libs/byte_utils.py
kitir/_libs/collection_utils.py
kitir/_libs/csv_utils.py
kitir/_libs/datetime_utils.py
kitir/_libs/decorator_utils.py
kitir/_libs/docker_utils.py
kitir/_libs/enum_utils.py
kitir/_libs/env_utils.py
kitir/_libs/exec_utils.py
kitir/_libs/file_utils.py
kitir/_libs/func_utils.py
kitir/_libs/linux_utils.py
kitir/_libs/log_utils.py
kitir/_libs/mail_utils.py
kitir/_libs/package_utils.py
kitir/_libs/sort_utils.py
kitir/_libs/ssh_utils.py
kitir/_libs/string_utils.py
kitir/_libs/wait_utils.py
kitir/_libs/tests/__init__.py
kitir/_libs/tests/test_exec_utils.py
kitir/_libs/tests/test_file_utils.py
kitir/_libs/tests/test_func_utils.py
kitir/_libs/tests/test_wait_utils.py
kitir/kits/__init__.py
kitir/kits/restful_api.py
kitir/kits/thread_pool.py
kitir/kits/virtual_interface.py
kitir/tests/__init__.py
kitir/tests/test_thread_pool.py
kitir-1.0.9.dist-info/LICENSE
kitir-1.0.9.dist-info/METADATA
kitir-1.0.9.dist-info/WHEEL
kitir-1.0.9.dist-info/top_level.txt
kitir-1.0.9.dist-info/RECORD
