Metadata-Version: 2.1
Name: kitir
Version: 1.0.9
Summary: A package with useful tools
Home-page: https://github.com/InbarRose/kitir
Author: Inbar Rose
Author-email: inbar.rose1@gmail.com
License: UNKNOWN
Platform: UNKNOWN
Classifier: Development Status :: 5 - Production/Stable
Classifier: Intended Audience :: Developers
Classifier: Topic :: Software Development :: Testing
Classifier: Programming Language :: Python :: 3
Classifier: Programming Language :: Python :: 3.7
Classifier: Programming Language :: Python :: Implementation :: CPython
Classifier: License :: OSI Approved :: MIT License
Classifier: Operating System :: OS Independent
Requires-Python: >=3.7.4
Requires-Dist: pytz
Requires-Dist: requests
